{
  "IdentityComponent": true,
  "Name": "none",
  "ObjectType": "EnemyTwo",

  "TransformComponent": true,
  "Position": [ 0.0, 0.0 ],
  "Scale": [ 70.0, 70.0 ],
  "Rotate": 0.0,

  "GraphicsComponent": true,
  "G.TypeId": 0,
  "G.FileName": "EnemyTwo.png",

  "AnimationComponent": true,
  "AnimationTypes": [
    {
      "AnimationType": "Shooter_enemy_sprite.json",
      "TimeDelay": 0.1,
      "AnimationName": "Death"
    },
    {
      "AnimationType": "Enemies1_sprite.json",
      "TimeDelay": 0.1,
      "AnimationName": "Move"
    }
  ],
  "StartAnim": "Move",

  "RigidBody2DComponent": true,
  "Mass": 5.0,
  "Friction": 0.1,
  "Static": false,

  "CircleCollider2DComponent": true,
  "ColliderTypeId": 2,
  "ColliderTag": 3,
  "ColliderTrigger": false,

  "AudioComponent": true,
  "A.TypeId": 0,
  "A.FileName": "audio_enemy.ogg",

  "LogicComponent": true,
  "Script2Id": [ "Enemy" ],
  "Script2Data": [
    {
      "Health": 3,
      "EnemyType": 1,
      "StunDuration": 0.5,
      "AttackRangeShoot": 4.0,
      "AttackRangeMelee": 0.0,
      "MoveSpeed": 3.0,
      "ChaseSpeed": 0.0,
      "ChaseDuration": 0.0
    }
  ]
}